{
  "indexes": [
    {
      "collectionGroup": "helferPunkte",
      "queryScope": "COLLECTION",
      "fields": [
        {
          "fieldPath": "userId",
          "order": "ASCENDING"
        },
        {
          "fieldPath": "eventDate",
          "order": "DESCENDING"
        }
      ]
    },
    {
      "collectionGroup": "news",
      "queryScope": "COLLECTION",
      "fields": [
        {
          "fieldPath": "type",
          "order": "ASCENDING"
        },
        {
          "fieldPath": "date",
          "order": "DESCENDING"
        }
      ]
    },
    {
      "collectionGroup": "notification",
      "queryScope": "COLLECTION",
      "fields": [
        {
          "fieldPath": "opened",
          "order": "ASCENDING"
        },
        {
          "fieldPath": "date",
          "order": "DESCENDING"
        }
      ]
    }
  ],
  "fieldOverrides": [
    {
      "collectionGroup": "attendees",
      "fieldPath": "id",
      "ttl": false,
      "indexes": [
        {
          "order": "ASCENDING",
          "queryScope": "COLLECTION"
        },
        {
          "order": "DESCENDING",
          "queryScope": "COLLECTION"
        },
        {
          "arrayConfig": "CONTAINS",
          "queryScope": "COLLECTION"
        },
        {
          "order": "ASCENDING",
          "queryScope": "COLLECTION_GROUP"
        }
      ]
    },
    {
      "collectionGroup": "contacts",
      "fieldPath": "email",
      "ttl": false,
      "indexes": [
        {
          "order": "ASCENDING",
          "queryScope": "COLLECTION"
        },
        {
          "order": "DESCENDING",
          "queryScope": "COLLECTION"
        },
        {
          "arrayConfig": "CONTAINS",
          "queryScope": "COLLECTION"
        },
        {
          "order": "ASCENDING",
          "queryScope": "COLLECTION_GROUP"
        }
      ]
    }
  ]
}
